{
  "itens" : [
    {
      "id": 1,
      "name": "Varejo 360",
      "img": "./assets/imagens/1.png",
      "data": " Qui, 09 Mar - 19:00",
      "local": "Sebrae - Recife"
    },
    {
      "id": 2,
      "name": "A Cor Purpura",
      "img": "./assets/imagens/2.png",
      "data": " Qui, 09 Mar - 19:00",
      "local": "Teatro do Parque - Recife"

    },
    {
     "id": 3,
     "name": "A Arte do Estoicismo",
     "img": "./assets/imagens/3.jpg",
     "data": " Qui, 09 Mar - 19:00",
     "local": "Online"

    },
    {
      "id": 4,
      "name": "Terra por elas Convida",
      "img": "./assets/imagens/4.jpg",
      "data": " Qui, 09 Mar - 19:00",
      "local": "Sebrae - Recife"

    },
    {
      "id": 5,
      "name": "Match Hall",
      "img": "./assets/imagens/5.png",
      "data": " Qui, 09 Mar - 19:00",
      "local": "Sebrae - Recife"

    }
  ]
}
